ortho_seq_code/__init__.py
ortho_seq_code/cli.py
ortho_seq_code/conftest.py
ortho_seq_code/constants_orthoseqs.py
ortho_seq_code/orthogonal_polynomial.py
ortho_seq_code/sr.py
ortho_seq_code-1.0.dist-info/LICENSE
ortho_seq_code-1.0.dist-info/METADATA
ortho_seq_code-1.0.dist-info/WHEEL
ortho_seq_code-1.0.dist-info/entry_points.txt
ortho_seq_code-1.0.dist-info/top_level.txt
ortho_seq_code-1.0.dist-info/RECORD
